Metadata-Version: 2.1
Name: odoo13-addon-connector-importer
Version: 13.0.1.7.0
Summary: This module takes care of import sessions.
Home-page: https://github.com/OCA/connector-interfaces
Author: Camptocamp, Odoo Community Association (OCA)
Author-email: support@odoo-community.org
License: AGPL-3
Platform: UNKNOWN
Classifier: Programming Language :: Python
Classifier: Framework :: Odoo
Classifier: License :: OSI Approved :: GNU Affero General Public License v3
Requires-Python: >=3.5
Requires-Dist: chardet
Requires-Dist: odoo13-addon-connector
Requires-Dist: odoo13-addon-queue-job
Requires-Dist: odoo (<13.1dev,>=13.0a)
Requires-Dist: pytz
Requires-Dist: pyyaml
